directaccess/__init__.py
directaccess-1.5.2.dist-info/LICENSE.md
directaccess-1.5.2.dist-info/METADATA
directaccess-1.5.2.dist-info/WHEEL
directaccess-1.5.2.dist-info/top_level.txt
directaccess-1.5.2.dist-info/RECORD
