Metadata-Version: 2.1
Name: directaccess
Version: 1.5.2
Summary: Enverus Direct Access API Python Client
Home-page: https://github.com/wchatx/direct-access-py
Author: Cole Howard
Author-email: wchatx@gmail.com
License: MIT
Keywords: enverus,drillinginfo,oil,gas
Platform: UNKNOWN
Classifier: Development Status :: 5 - Production/Stable
Classifier: Intended Audience :: Developers
Classifier: Intended Audience :: End Users/Desktop
Classifier: License :: OSI Approved :: MIT License
Classifier: Operating System :: OS Independent
Classifier: Programming Language :: Python :: 2
Classifier: Programming Language :: Python :: 3
Requires-Dist: requests (>=2.16.0)
Requires-Dist: unicodecsv (==0.14.1)
Requires-Dist: urllib3 (>=1.26.0)
Provides-Extra: pandas
Requires-Dist: pandas (>=0.24.0) ; extra == 'pandas'
